[{"Titulo": "Nota \u00e0 Imprensa - 158\u00aa. Reuni\u00e3o", "Conteudo": " Dando seguimento ao processo de ajuste das condi\u00e7\u00f5es monet\u00e1rias, o Copom decidiu elevar a taxa Selic para 12,00% a.a., sem vi\u00e9s, por cinco votos a favor e dois votos pelo aumento da taxa Selic em 0,50 p.p.Considerando o balan\u00e7o de riscos para a infla\u00e7\u00e3o, o ritmo ainda incerto de modera\u00e7\u00e3o da atividade dom\u00e9stica, bem como a complexidade que ora envolve o ambiente internacional, o Comit\u00ea entende que, neste momento, a implementa\u00e7\u00e3o de ajustes das condi\u00e7\u00f5es monet\u00e1rias por um per\u00edodo suficientemente prolongado \u00e9 a estrat\u00e9gia mais adequada para garantir a converg\u00eancia da infla\u00e7\u00e3o para a meta em 2012. ", "dataPublicacao": "2011-04-20T03:00:00Z", "ultimaAtualizacao": "2016-10-18T20:01:25Z", "mostrarRodape": false, "mostrarCabecalho": false}]