[{"Url": null, "LinkPagina": "/publicacoes/atascopom/cronologicos", "data": "2001-02-21T03:00:00Z", "Titulo": "56\u00aa Reuni\u00e3o", "DataReferencia": "2001-02-01T02:00:00Z", "Edicao": null, "Volume": null, "Introducao": "", "BoxDestaque": null, "Grafico": null, "OutrasInformacoes": "\n\n  \n    Sum\u00e1rio\n\n    \n      Demanda e oferta agregadas \n\n      \n        Ambiente externo\n      \n\n      \n        Pre\u00e7os\n      \n\n      \n        Mercado monet\u00e1rio e opera\u00e7\u00f5es de mercado aberto\n      \n\n      \n        Avalia\u00e7\u00e3o prospectiva das tend\u00eancias da infla\u00e7\u00e3o\n      \n\n      \n        Diretrizes de pol\u00edtica monet\u00e1ria\n      \n    \n    \n    \u00a0\n\n    \n      Data: 13 e 14.2.2001\n    \n\n    \n      Local: Sala de reuni\u00f5es do 8\u00ba andar (no dia 13) e 20\u00ba andar (no dia 14) do Edif\u00edcio-Sede do Banco Central - Bras\u00edlia - DF\n    \n\n    \n      Hor\u00e1rio de in\u00edcio: 15:40 h dia 13 e 17:40 h dia 14\n    \n\n    \n      Hor\u00e1rio de t\u00e9rmino: 18:40 dia 13 e 19:00 h dia 14\n    \n\n    \n      Presentes:\n    \n\n    \n      Membros da Diretoria Colegiada\n    \n\n    \n      Arminio Fraga Neto - Presidente\n    \n\n    \n      Carlos Eduardo de Freitas\n    \n\n    \n      Daniel Luiz Gleizer\n    \n\n    \n      Edison Bernardes dos Santos\n    \n\n    \n      Ilan Goldfajn\n    \n\n    \n      Luiz Fernando Figueiredo\n    \n\n    \n      S\u00e9rgio Darcy da Silva Alves\n    \n\n    \n      Tereza Cristina Grossi Togni\n    \n\n    \n      Chefes de Departamento (todos presentes no dia 13)\n    \n\n    \n      Altamir Lopes - Departamento Econ\u00f4mico (DEPEC)\n    \n\n    \n      Carlos Yoshitaka Urata - Departamento de Opera\u00e7\u00f5es das Reservas Internacionais (DEPIN)\n    \n\n    \n      Jos\u00e9 Antonio Marciano - Departamento de Opera\u00e7\u00f5es Banc\u00e1rias (DEBAN)\n    \n\n    \n      Alexandre Antonio Tombini - Departamento de Estudos e Pesquisas (DEPEP)\n    \n\n    \n      Eduardo Hitiro Nakao - Departamento de Opera\u00e7\u00f5es do Mercado Aberto (DEMAB)\n    \n\n    \n      Demais participantes (todos presentes no dia 13)\n    \n\n    \n      Alexandre Pundek Rocha - Consultor da Diretoria\n    \n\n    \n      Ant\u00f4nio Carlos Monteiro - Secret\u00e1rio-Executivo do Banco Central do Brasil\n    \n\n    \n      Gustavo Bussinger - Consultor do DEPEC\n    \n\n    \n      Jo\u00e3o Borges - Assessor de Imprensa (ASIMP)\n    \n\n    \n      A Diretoria Colegiada analisou a evolu\u00e7\u00e3o recente e as perspectivas da economia brasileira e da economia internacional no contexto do novo regime de pol\u00edtica monet\u00e1ria, cujo objetivo \u00e9 atingir as metas fixadas pelo Governo para a infla\u00e7\u00e3o.\n    \n\n    \n      \u00a0\n    \n\n    \n      Demanda e oferta agregadas\n    \n\n    \n      No final do ano passado, os indicadores de oferta agregada mostraram expans\u00e3o forte, com crescente utiliza\u00e7\u00e3o m\u00e9dia da capacidade instalada e aumento do emprego na ind\u00fastria.\n    \n\n    \n      O IBGE divulgou o PIB de 2000, que cresceu 4,2%, performance liderada pela expans\u00e3o de 4,8% do produto industrial, com destaque para a ind\u00fastria de transforma\u00e7\u00e3o. A agropecu\u00e1ria e os servi\u00e7os apresentaram evolu\u00e7\u00e3o positiva mas menos intensa, respectivamente de 2,9% e de 3,6%. Observe-se que o IBGE retificou o resultado do terceiro trimestre, cujo crescimento passou de 3,8% para 4,1%.\n    \n\n    \n      Em dezembro, a produ\u00e7\u00e3o industrial cresceu 7,2% em rela\u00e7\u00e3o a novembro, na s\u00e9rie dessazonalizada. O crescimento da produ\u00e7\u00e3o em dezembro foi generalizado, alcan\u00e7ando 14 dos 20 ramos pesquisados e todas as categorias de uso. Nestas, o segmento de bens de consumo dur\u00e1veis apresentou o maior acr\u00e9scimo (23%). No ano, a produ\u00e7\u00e3o industrial acumulou expans\u00e3o de 6,5%.\n    \n\n    \n      Em rela\u00e7\u00e3o ao mercado de trabalho, permaneceu a tend\u00eancia de crescimento do emprego e da produtividade. A taxa de desemprego aberto recuou de 6,8% em novembro para 6,0% em dezembro, em termos dessazonalizados, refletindo em especial a diminui\u00e7\u00e3o da popula\u00e7\u00e3o economicamente ativa (PEA). Todos os setores da atividade econ\u00f4mica apresentaram redu\u00e7\u00e3o no desemprego em dezembro. Dados de crescimento da produtividade do trabalho, dispon\u00edveis at\u00e9 outubro, mostraram crescimento acumulado no ano de 6%.\n    \n\n    \n      O n\u00edvel de utiliza\u00e7\u00e3o da capacidade instalada alcan\u00e7ou 82% em janeiro, ap\u00f3s ter atingido 84,1% em outubro de 2000, segundo a Sondagem Conjuntural da Ind\u00fastria de Transforma\u00e7\u00e3o, da Funda\u00e7\u00e3o Getulio Vargas. Descontadas as influ\u00eancias sazonais, observou-se crescimento de 0,6%. O n\u00edvel de janeiro, mesmo superando o de janeiro de 2000 (81%), \u00e9 bem inferior ao pico de 86% ocorrido em abril de 1995.\n    \n\n    \n      Por setores de atividade, o n\u00edvel de 77% alcan\u00e7ado pelas ind\u00fastrias de bens de consumo situou-se abaixo da m\u00e9dia do m\u00eas e do pico de 87% registrado em outubro de 1995. Tamb\u00e9m nas ind\u00fastrias de bens de capital, o patamar de janeiro (81%) foi inferior ao da m\u00e9dia da ind\u00fastria e ao m\u00e1ximo de 86% atingido em outubro de 1997. Em rela\u00e7\u00e3o aos 23 g\u00eaneros industriais pesquisados, em nove a utiliza\u00e7\u00e3o da capacidade n\u00e3o alcan\u00e7ou 80%, com destaque para produtos farmac\u00eauticos, 64,4%, material de transporte, 77,4%, e mec\u00e2nica, 75,5%. Apenas na ind\u00fastria t\u00eaxtil registrou-se pico da utiliza\u00e7\u00e3o em janeiro de 2001 (91%). Observe-se ainda que em alguns g\u00eaneros, como papel e papel\u00e3o e borracha, operar utilizando intensamente a capacidade instalada \u00e9 comportamento t\u00edpico dessas ind\u00fastrias.\n    \n\n    \n      O ritmo expansionista se manteve neste in\u00edcio do ano, evidenciado pelo crescimento da demanda agregada, tend\u00eancia sustentada pela expans\u00e3o do cr\u00e9dito e pela melhora nas expectativas dos consumidores, face aos resultados favor\u00e1veis dos principais indicadores macroecon\u00f4micos.\n    \n\n    \n      As vendas industriais de autove\u00edculos aumentaram 28,1% em janeiro em rela\u00e7\u00e3o ao mesmo m\u00eas do ano anterior, com eleva\u00e7\u00e3o de 29,1% nas vendas para o mercado interno e de 23,5% nas exporta\u00e7\u00f5es.\n    \n\n    \n      Segundo dados preliminares da Federa\u00e7\u00e3o do Com\u00e9rcio do Estado de S\u00e3o Paulo (FCESP), o faturamento real do com\u00e9rcio varejista na regi\u00e3o metropolitana, em termos dessazonalizados, cresceu 1,3% em janeiro frente ao m\u00eas anterior e 16,3% na compara\u00e7\u00e3o com janeiro de 2000. As vendas de bens de consumo dur\u00e1veis e n\u00e3o-dur\u00e1veis comandaram a expans\u00e3o, estimuladas pela melhora nas condi\u00e7\u00f5es do cr\u00e9dito.\n    \n\n    \n      De fato, conforme levantamento preliminar para janeiro, o saldo dos cr\u00e9ditos com recursos livres cresceu 1,9% no m\u00eas, composto por queda de 0,2% nos cr\u00e9ditos destinados a pessoas jur\u00eddicas e crescimento de 6,3% nos destinados a pessoas f\u00edsicas. Esse resultado indica continuidade da contribui\u00e7\u00e3o das opera\u00e7\u00f5es de cr\u00e9dito para a sustenta\u00e7\u00e3o da demanda agregada. O cr\u00e9dito total na economia, incluindo os recursos livres e os direcionados, atingiu R$ 315,9 bilh\u00f5es (28,7% do PIB), com queda de 0,4%% no m\u00eas.\n    \n\n    \n      N\u00e3o obstante o crescimento do cr\u00e9dito, a inadimpl\u00eancia no sistema banc\u00e1rio continuou moderada. Os cr\u00e9ditos sem atraso corresponderam a 92,8% do total em janeiro desse ano e os com atraso acima de 90 dias a 3,1%. No com\u00e9rcio, em contraste, houve aumento possivelmente transit\u00f3rio na taxa l\u00edquida de inadimpl\u00eancia, que em S\u00e3o Paulo atingiu 9,3% em janeiro, ante 4,2% em dezembro, segundo o Servi\u00e7o de Prote\u00e7\u00e3o ao Cr\u00e9dito da Associa\u00e7\u00e3o Comercial de S\u00e3o Paulo. Tamb\u00e9m a participa\u00e7\u00e3o dos cheques devolvidos por insufici\u00eancia de fundos sobre o total de cheques compensados elevou-se em janeiro, atingindo 4,2%, ap\u00f3s 3,5% registrados em dezembro.\n    \n\n    \n      O crescimento forte da demanda agregada impulsionou os investimentos. Os indicadores de investimento continuaram em expans\u00e3o, com destaque para a produ\u00e7\u00e3o de bens de capital, que cresceu 12,7% em 2000, principalmente os industriais seriados e aqueles voltados para os setores agr\u00edcola e de transportes. As importa\u00e7\u00f5es de bens de capital cresceram 6,8% em dezembro e 33,1% em janeiro, em termos dessazonalizados. Destaque-se tamb\u00e9m o crescimento dos desembolsos do BNDES ao setor produtivo em 57,1% em janeiro, em rela\u00e7\u00e3o ao mesmo m\u00eas de 2000.\n    \n\n    \n      O setor de constru\u00e7\u00e3o civil, com peso expressivo nas estimativas de investimento e do PIB, apresentou desempenho menos din\u00e2mico no ano passado, como mostrou a expans\u00e3o anual de 2% na produ\u00e7\u00e3o de insumos. No entanto, a produ\u00e7\u00e3o de bens de capital para constru\u00e7\u00e3o cresceu 15% em 2000 e o n\u00edvel e atividade tem se recuperado nos \u00faltimos meses. A taxa de desemprego no setor passou de 7,5% em novembro para 5,7% em dezembro (dados observados) e as vendas de materiais de constru\u00e7\u00e3o em janeiro cresceram 24,3% em compara\u00e7\u00e3o com mesmo m\u00eas do ano passado.\n    \n\n    \n      O aumento da demanda agregada tem sido parcialmente atendido por bens produzidos no exterior. Em janeiro o saldo da balan\u00e7a comercial atingiu d\u00e9ficit de US$\u00a0479\u00a0milh\u00f5es, em parte compensado por super\u00e1vit de US$\u00a017\u00a0milh\u00f5es nas duas primeiras semanas de fevereiro. As importa\u00e7\u00f5es tiveram crescimento generalizado, com destaque para bens de capital (+54,3%) e mat\u00e9rias-primas e bens intermedi\u00e1rios (+29,0%). Foi not\u00e1vel o aumento dos volumes de com\u00e9rcio internacional. Em janeiro, a balan\u00e7a comercial registrou exporta\u00e7\u00f5es di\u00e1rias m\u00e9dias de US$\u00a0206,3\u00a0milh\u00f5es e importa\u00e7\u00f5es de US$ 228 milh\u00f5es, acusando altas de 25,5% e de 34,2% relativamente a igual m\u00eas de 2000. Destacou-se o crescimento das exporta\u00e7\u00f5es de produtos prim\u00e1rios como soja, min\u00e9rio de ferro, celulose e a\u00e7\u00facar, refletindo a continuidade da expans\u00e3o dos volumes embarcados. Nas duas primeiras semanas de fevereiro, houve crescimento das m\u00e9dias di\u00e1rias de 6,1% para as exporta\u00e7\u00f5es e de 6,9% para as importa\u00e7\u00f5es, em rela\u00e7\u00e3o a fevereiro de 2000.\n    \n\n    \n      Parte do d\u00e9ficit da balan\u00e7a comercial em janeiro pode ser resultado de fatores tempor\u00e1rios. As importa\u00e7\u00f5es de combust\u00edveis e lubrificantes, em janeiro, situaram-se 14,9% acima da m\u00e9dia mensal de 2000. Por sua vez, a eleva\u00e7\u00e3o das compras de bens de capital em janeiro pode estar associada n\u00e3o somente ao aumento do produto industrial, mas tamb\u00e9m, a partir desse m\u00eas, \u00e0 redu\u00e7\u00e3o da tarifa de importa\u00e7\u00e3o de 18% para 14% (al\u00edquota da Tarifa Externa Comum do Mercosul para essa categoria) e \u00e0 amplia\u00e7\u00e3o da lista de ex-tarif\u00e1rios, que estabeleceu em 4% a al\u00edquota do imposto de importa\u00e7\u00e3o para 1.584 itens, relacionados principalmente aos setores qu\u00edmico, petroqu\u00edmico, papel e celulose, t\u00eaxtil, montadoras de ve\u00edculos e autope\u00e7as. Esses itens, somados a 384 itens de inform\u00e1tica e telecomunica\u00e7\u00f5es, tamb\u00e9m inclu\u00eddos na lista de ex-tarif\u00e1rios, foram respons\u00e1veis por cerca de 8% da pauta de importa\u00e7\u00e3o de bens de capital at\u00e9 setembro de 2000.\n    \n\n    \n      \u00a0\n    \n\n    \n      Ambiente externo\n    \n\n    \n      O crescimento do produto nos pa\u00edses industrializados deve desacelerar este ano, liderado pelo recuo do crescimento norte-americano para a faixa de 1,75% a 2,5%, de acordo com as expectativas correntes no mercado. Neste pa\u00eds, o \u00edndice NAPM dos gerentes de compras relativo \u00e0 ind\u00fastria manufatureira atingiu 41,2% em janeiro, o n\u00edvel mais baixo dos \u00faltimos dois anos. A produ\u00e7\u00e3o industrial dessazonalizada reduziu-se 0,6% em dezembro em rela\u00e7\u00e3o ao m\u00eas anterior. J\u00e1 a taxa de desemprego avan\u00e7ou de 4,0% em dezembro para 4,2% em janeiro.\n    \n\n    \n      Na reuni\u00e3o de janeiro, o Federal Open Market Comittee decidiu por nova queda de 50 pontos-base na meta para a taxa de juros b\u00e1sica, reduzida para 5,5% ao ano. Em seu comunicado, o Comit\u00ea referiu-se \u00e0 necessidade de uma resposta r\u00e1pida e firme da pol\u00edtica monet\u00e1ria num cen\u00e1rio de queda mais acentuada da confian\u00e7a dos consumidores e das empresas que j\u00e1 afeta o crescimento da produ\u00e7\u00e3o industrial. Na mesma data, a taxa de redesconto foi reduzida em 50 pontos-base, para 5% ao ano.\n    \n\n    \n      Quanto aos pa\u00edses da \u00c1rea do Euro, espera-se em 2001 um crescimento entre 2,3% e 2,8%, provavelmente acima do crescimento nos EUA. Em dezembro, a taxa de desemprego ficou est\u00e1vel em 8,7%. A produ\u00e7\u00e3o industrial aumentou 0,6% em novembro, acumulando crescimento anual de 4,7%. A infla\u00e7\u00e3o medida pelo \u00edndice de pre\u00e7os ao consumidor harmonizado atingiu 2,6% em 2000, recuando em rela\u00e7\u00e3o aos 2,9% anuais registrados at\u00e9 novembro. No entanto, os indicadores de confian\u00e7a mantiveram a tend\u00eancia de recuo iniciada em setembro do ano passado.\n    \n\n    \n      No Jap\u00e3o, o consumo permanece retra\u00eddo enquanto os indicadores de investimento registram alguma rea\u00e7\u00e3o: as encomendas \u00e0 ind\u00fastria aumentaram 15,4% em novembro, relativamente a igual m\u00eas do ano anterior, e o in\u00edcio de constru\u00e7\u00e3o de resid\u00eancias elevou-se 10,6% em dezembro ante dezembro de 1999. O saldo comercial acumulado em 12 meses registrou queda de 4,4% em dezembro, mantendo trajet\u00f3ria descendente, enquanto a taxa de desemprego permaneceu em 4,8% nos \u00faltimos dois meses de 2000. A produ\u00e7\u00e3o industrial acumulou crescimento de 5,2% no ano.\n    \n\n    \n      O pre\u00e7o internacional do petr\u00f3leo permanece vol\u00e1til. Nos mercados \u00e0 vista, as cota\u00e7\u00f5es elevaram-se nas primeiras semanas de fevereiro, mas os mercados futuros mant\u00eam expectativas de quedas ao longo do ano.\n    \n\n    \n      Finalmente, a Argentina est\u00e1 recuperando a confian\u00e7a dos agentes, como se depreende da evolu\u00e7\u00e3o das taxas de juros e do custo das coloca\u00e7\u00f5es dos t\u00edtulos do Tesouro realizadas desde o in\u00edcio do ano. Nesse sentido, a diferen\u00e7a entre as taxas de juros das opera\u00e7\u00f5es de 30 dias em d\u00f3lares e em pesos situava-se em 0,375% no dia 13 de fevereiro, com as taxas alcan\u00e7ando 6,875% a.a e 7,25% a.a., respectivamente, n\u00edveis inferiores aos vigentes antes da crise.\n    \n\n    \n      \u00a0\n    \n\n    \n      Pre\u00e7os\n    \n\n    \n      O IPCA apresentou alta de 0,57% em janeiro, ante 0,59% em dezembro. A redu\u00e7\u00e3o na taxa de varia\u00e7\u00e3o dos combust\u00edveis, que exerceu impacto significativo em dezembro, foi compensada pela alta dos alimentos e das mensalidades escolares, de car\u00e1ter sazonal. Tamb\u00e9m importantes foram as press\u00f5es decorrentes dos reajustes dos pre\u00e7os das passagens de \u00f4nibus urbanos em algumas capitais, da tarifa de energia el\u00e9trica e da incid\u00eancia do ICMS sobre energia em Bel\u00e9m. Com o resultado de janeiro, a varia\u00e7\u00e3o do IPCA nos \u00faltimos 12 meses situou-se em 5,92%.\n    \n\n    \n      O IGP-DI subiu 0,49% em janeiro, resultado das varia\u00e7\u00f5es de 0,40% no \u00edndice de pre\u00e7os no atacado, de 0,64% no \u00edndice de pre\u00e7os ao consumidor e de 0,58% no custo da constru\u00e7\u00e3o. No atacado, destaca-se a queda de 0,62% nos pre\u00e7os dos produtos agr\u00edcolas provocada sobretudo pela redu\u00e7\u00e3o de 2,9% nos pre\u00e7os de animais e derivados, particularmente aves. A varia\u00e7\u00e3o dos pre\u00e7os industriais recuou de 1,15% em dezembro para 0,78% em janeiro. No IPC, a eleva\u00e7\u00e3o deveu-se principalmente aos itens educa\u00e7\u00e3o, alimentos e despesas diversas, contribuindo ainda o reajuste de \u00f4nibus urbano em algumas capitais. O n\u00facleo do IPC subiu 0,44%, ante 0,50% em dezembro.\n    \n\n    \n      \u00a0\n    \n\n    \n      Mercado monet\u00e1rio e opera\u00e7\u00f5es de mercado aberto\n    \n\n    \n      O per\u00edodo compreendido entre 17 de janeiro e 13 de fevereiro caracterizou-se por impacto monet\u00e1rio contracionista (de R$ 1,8 bilh\u00e3o nas opera\u00e7\u00f5es definitivas com t\u00edtulos federais) e alongamento de prazos.\n    \n\n    \n      Em quatro ofertas p\u00fablicas tradicionais, o Tesouro Nacional vendeu LTNs vincendas em doze e dezoito meses. J\u00e1 em leil\u00e3o \u00fanico de oferta firme, foram vendidas LTNs de 26 meses, o prazo mais longo para t\u00edtulos da esp\u00e9cie. O volume financeiro dessas coloca\u00e7\u00f5es alcan\u00e7ou R$\u00a010,4 bilh\u00f5es frente a resgates de R$ 10,2 bilh\u00f5es, considerando R$ 2,5 bilh\u00f5es resultantes de dois leil\u00f5es de compra.\n    \n\n    \n      O Banco Central efetuou no per\u00edodo o giro integral do principal atualizado dos t\u00edtulos cambiais vincendos, atrav\u00e9s de tr\u00eas leil\u00f5es de NBC-Es, com vencimentos para dois, tr\u00eas e quatro anos, respectivamente. O resultado desses eventos evidencia que os agentes econ\u00f4micos est\u00e3o demandando hedge cambial para prazos mais longos.\n    \n\n    \n      No per\u00edodo, ocorreram ainda quatro ofertas competitivas de LFTs, a primeira com prazo de quatro anos e as demais com prazo de cinco anos. Mesmo com o alongamento, registrou-se redu\u00e7\u00e3o sistem\u00e1tica do des\u00e1gio, de 0,09% para 0,04% ao ano, do primeiro para o \u00faltimo leil\u00e3o.\n    \n\n    \n      Ainda no mercado prim\u00e1rio, ratificando a tend\u00eancia de alongamento dos prazos, o Tesouro Nacional realizou a segunda oferta de NTN-Cs de trinta anos. A venda totalizou R$\u00a02,5\u00a0bilh\u00f5es, com 52% deste montante liquidado com o uso de cr\u00e9ditos securitizados de responsabilidade do Tesouro Nacional e de LFT-B.\n    \n\n    \n      \u00a0\n    \n\n    \n      Avalia\u00e7\u00e3o prospectiva das tend\u00eancias da infla\u00e7\u00e3o\n    \n\n    \n      Os choques identificados e os seus impactos foram reavaliados de acordo com as novas informa\u00e7\u00f5es dispon\u00edveis. O cen\u00e1rio considerado nas simula\u00e7\u00f5es contempla as hip\u00f3teses listadas a seguir:\n    \n\n    \n      \n        \n          a infla\u00e7\u00e3o observada em janeiro (0,57%) superou ligeiramente o valor esperado (0,50%);\n        \n      \n\n      \n        \n          a curva de pre\u00e7os atualmente impl\u00edcita nos contratos futuros de petr\u00f3leo do tipo Brent deslocou-se cerca de US$ 2,00 para cima em rela\u00e7\u00e3o \u00e0 observada na reuni\u00e3o anterior. Com isso, e o atual patamar da taxa de c\u00e2mbio no mercado, a queda de 6,5% antes esperada para o pre\u00e7o da gasolina ao consumidor no segundo trimestre pode n\u00e3o ocorrer, mas apenas redu\u00e7\u00f5es menores nos \u00faltimos dois trimestres de 2001;\n        \n      \n\n      \n        \n          o reajuste para as tarifas de energia el\u00e9trica foi reestimado \u00e0 luz das autoriza\u00e7\u00f5es j\u00e1 concedidas pela Aneel neste ano. O reajuste total da energia el\u00e9trica previsto para 2001 passou de 12% para 15,8%, com aumentos maiores nos dois \u00faltimos trimestres. Para o conjunto de pre\u00e7os administrados, incluindo combust\u00edveis e sal\u00e1rio m\u00ednimo, o reajuste m\u00e9dio esperado chega a 8,5%, com contribui\u00e7\u00e3o direta de 1,9 ponto percentual para a infla\u00e7\u00e3o no ano;\n        \n      \n\n      \n        \n          de acordo com as proje\u00e7\u00f5es dos contratos futuros, a hip\u00f3tese para a trajet\u00f3ria da taxa dos fed funds inclui redu\u00e7\u00e3o adicional de 50 pontos-base no segundo trimestre de 2001. Assim, essa taxa cairia dos atuais 5,5% a.a. para 5% a.a., estabilizando-se em seguida neste patamar;\n        \n      \n\n      \n        \n          foi mantida a hip\u00f3tese considerada na reuni\u00e3o anterior de obten\u00e7\u00e3o de super\u00e1vit prim\u00e1rio de acordo com as metas estabelecidas pela pol\u00edtica fiscal. Esta hip\u00f3tese, juntamente com menores taxas de juros nos EUA, queda de pre\u00e7os de petr\u00f3leo e a aprecia\u00e7\u00e3o do euro frente ao d\u00f3lar pode permitir que a percep\u00e7\u00e3o de risco Brasil continue melhorando gradativamente.\n        \n      \n    \n\n    \n      O crescimento do PIB foi ajustado de acordo com os dados publicados pelo IBGE.\n    \n\n    \n      Dos exerc\u00edcios de simula\u00e7\u00e3o com o cen\u00e1rio considerado no modelo b\u00e1sico (estrutural), concluiu-se que a manuten\u00e7\u00e3o da taxa de juros no n\u00edvel atual de 15,25% a.a. permite o cumprimento das metas de infla\u00e7\u00e3o em 2001 e 2002. Quando se toma por base a trajet\u00f3ria de taxa de juros nominais esperada pelo mercado (expressa na pesquisa mensal coletada pelo Banco Central), que atinge 13,8% a.a. no final de 2001, as proje\u00e7\u00f5es de infla\u00e7\u00e3o ficam um pouco acima da meta para 2001, apesar de situarem-se confortavelmente dentro da margem de \u00b12%.\n    \n\n    \n      O n\u00facleo de infla\u00e7\u00e3o do IPCA, calculado pelo m\u00e9todo das m\u00e9dias aparadas, voltou para o n\u00edvel de 0,42% em janeiro, depois de permanecer estacionado em cerca de 0,33% nos dois meses anteriores. No entanto, a maior parte dos itens exclu\u00eddos por estarem na cauda superior da distribui\u00e7\u00e3o pertence aos grupos alimenta\u00e7\u00e3o no domic\u00edlio e educa\u00e7\u00e3o. Os aumentos observados nesses itens s\u00e3o caracteristicamente tempor\u00e1rios, ou seja, n\u00e3o devem se repetir nos pr\u00f3ximos meses. Essa an\u00e1lise \u00e9 corroborada pelos n\u00facleos do IPCA calculados por exclus\u00e3o. Retirando a influ\u00eancia dos pre\u00e7os administrados, a varia\u00e7\u00e3o acumulada do IPCA nos \u00faltimos 12 meses caiu para 3,2% em janeiro e mant\u00e9m a tend\u00eancia de queda iniciada em setembro. J\u00e1 o n\u00facleo da infla\u00e7\u00e3o medida pelo IPC-BR, divulgado pela Funda\u00e7\u00e3o Getulio Vargas, caiu de 0,50% para 0,44%, seguindo o mesmo padr\u00e3o declinante ocorrido no mesmo per\u00edodo de 2000.\n    \n\n    \n      A mediana das expectativas para a varia\u00e7\u00e3o do IPCA coletadas por pesquisa di\u00e1ria do Banco Central manteve-se em 4,20% para 2001, mas reduziu-se de 3,82% para 3,75% para 2002.\n    \n\n    \n      \u00a0\n    \n\n    \n      Diretrizes de pol\u00edtica monet\u00e1ria\n    \n\n    \n      Os indicadores dispon\u00edveis de demanda agregada continuam mostrando crescimento de forma equilibrada entre seus diversos componentes. A demanda para consumo permanece firme, apoiada na expans\u00e3o do cr\u00e9dito e na melhora das expectativas. A demanda por investimento, que vinha sendo direcionada ao segmento de bens dur\u00e1veis, d\u00e1 sinais de voltar-se tamb\u00e9m para o segmento da constru\u00e7\u00e3o civil, a julgar pelo aumento da demanda por bens de capital e outros insumos da ind\u00fastria de constru\u00e7\u00e3o. O consumo do setor p\u00fablico permanece est\u00e1vel, com o cumprimento consistente das metas fixadas para a pol\u00edtica fiscal. O ritmo de crescimento das exporta\u00e7\u00f5es est\u00e1 compat\u00edvel com as expectativas para essa \u00e9poca do ano, apesar de n\u00e3o ser suficiente ainda para obten\u00e7\u00e3o de super\u00e1vit na balan\u00e7a comercial, dado o avan\u00e7o r\u00e1pido das importa\u00e7\u00f5es, principalmente de bens intermedi\u00e1rios e de capital.\n    \n\n    \n      A oferta agregada vem acompanhando o ritmo de crescimento da demanda. A produ\u00e7\u00e3o industrial continua vigorosa, o que se reflete em aumento da utiliza\u00e7\u00e3o da capacidade instalada, mas sem implicar em obst\u00e1culos detect\u00e1veis \u00e0 manuten\u00e7\u00e3o do crescimento em um cen\u00e1rio de estabilidade de pre\u00e7os. As perspectivas para a safra agr\u00edcola 2000/2001 permanecem positivas, com proje\u00e7\u00f5es de recorde de produ\u00e7\u00e3o de gr\u00e3os, embora em algumas culturas, como arroz e feij\u00e3o, as estimativas tenham sido revistas para baixo. O mercado de trabalho tem apresentado melhora, com taxas de desemprego menores e sem desequil\u00edbrios que apontem press\u00f5es pelo lado dos custos.\n    \n\n    \n      Em s\u00edntese, o balan\u00e7o de oferta e demanda n\u00e3o indica press\u00f5es sobre os \u00edndices de pre\u00e7os no horizonte relevante para o regime de metas para a infla\u00e7\u00e3o. Contudo, o crescimento firme da economia tem exercido impacto sobre a balan\u00e7a comercial, cujo saldo acumulado vem declinando desde o \u00faltimo quadrimestre de 2000, influenciando as expectativas no mercado de c\u00e2mbio. Em contraponto, as condi\u00e7\u00f5es de financiamento do balan\u00e7o de pagamentos continuam favor\u00e1veis e a avalia\u00e7\u00e3o do risco Brasil no exterior tem melhorado pela qualidade dos fundamentos dom\u00e9sticos e apesar da redu\u00e7\u00e3o no fluxo de investimentos diretos prevista para este ano.\n    \n\n    \n      O cen\u00e1rio externo apresenta incertezas relevantes ainda n\u00e3o dissipadas. O comportamento recente dos pre\u00e7os internacionais do petr\u00f3leo, depois do corte da produ\u00e7\u00e3o dos pa\u00edses integrantes da OPEP em fevereiro, voltou a caracterizar-se por acentuada volatilidade. A velocidade de queda dos pre\u00e7os internacionais do petr\u00f3leo tem sido menor do que projetavam os mercados futuros. Como o mecanismo de reajuste dos pre\u00e7os dom\u00e9sticos dos derivados de petr\u00f3leo em 2001 est\u00e1 diretamente ligado ao pre\u00e7o internacional, e como o peso desses derivados no IPCA \u00e9 elevado, a volatilidade externa transmite imprecis\u00e3o \u00e0s estimativas da infla\u00e7\u00e3o. No tocante \u00e0 economia mundial, as perspectivas de menor crescimento dos pa\u00edses industrializados parecem confirmar-se, dada a desacelera\u00e7\u00e3o do ritmo de atividade nos EUA apontada pelas estat\u00edsticas mais recentes. Conforme esperado pelos mercados, essas perspectivas t\u00eam levado ao abrandamento da pol\u00edtica monet\u00e1ria nos Estados Unidos, com o objetivo de evitar movimentos bruscos indesej\u00e1veis.\n    \n\n    \n      O comportamento recente da infla\u00e7\u00e3o est\u00e1 em linha com as percep\u00e7\u00f5es do Copom. No entanto, pelo terceiro ano consecutivo, a varia\u00e7\u00e3o dos pre\u00e7os administrados, em cuja forma\u00e7\u00e3o predominam componentes inerciais, deve superar por larga margem o valor da meta de infla\u00e7\u00e3o para o ano. Os reajustes de tarifas de energia el\u00e9trica concedidos neste in\u00edcio de ano para regi\u00f5es n\u00e3o abrangidas pelo IPCA, por exemplo, foram superiores \u00e0 infla\u00e7\u00e3o acumulada dos \u00edndices gerais de pre\u00e7os nos doze meses antecedentes. Outro pre\u00e7o importante \u00e9 o dos combust\u00edveis, que variar\u00e1 trimestralmente de acordo com as cota\u00e7\u00f5es m\u00e9dias do petr\u00f3leo e da taxa de c\u00e2mbio. Com esses fatores considerados, os pre\u00e7os administrados contribuem com aproximadamente metade do valor da meta para 2001. As expectativas de infla\u00e7\u00e3o do mercado para 2001 e 2002 praticamente n\u00e3o se alteraram desde a \u00faltima reuni\u00e3o do Copom, mantendo-se em sintonia com as metas para esses dois anos.\n    \n\n    \n      Diante disso, o Copom decidiu manter a meta para a taxa Selic em 15,25% ao ano.\n    \n\n    \n      Ao final da reuni\u00e3o, foi registrado que o Comit\u00ea voltaria a reunir-se em 20 de mar\u00e7o de 2001, \u00e0s 15:00 h, para as apresenta\u00e7\u00f5es t\u00e9cnicas e no dia seguinte, \u00e0s 16:30 h, para deliberar sobre as diretrizes de pol\u00edtica monet\u00e1ria, conforme estabelecido no Calend\u00e1rio das Reuni\u00f5es Ordin\u00e1rias do Copom, divulgado pelo Comunicado n\u00ba 8.018, de 22.11.2000, do Banco Central.\n    \n\n    \n      \u00a0\n    \n\n    \n      Alexandre Antonio Tombini\n    \n\n    \n      Notas revisadas pela Diretoria\n    \n  \n  ", "ImagemCapa": "/content/publicacoes/PublishingImages/Capas/atascopom/capa-atascopom.png", "Id": 64, "EsconderCapa": true, "EsconderDataReferencia": null}]